ptcal/__init__.py
ptcal/calibrator.py
ptcal/core.py
ptcal/plotting.py
ptcal/sensor.py
ptcal-0.1.4.dist-info/licenses/LICENSE
ptcal-0.1.4.dist-info/METADATA
ptcal-0.1.4.dist-info/WHEEL
ptcal-0.1.4.dist-info/top_level.txt
ptcal-0.1.4.dist-info/RECORD
