Metadata-Version: 2.4
Name: ptcal
Version: 0.1.4
Summary: High precision calibration tool for Pt100/Pt25 sensors (ITS-90 & CVD)
Author-email: Rodrigue Scholz <rodrigue.scholz@gmail.com>
License: MIT License
Project-URL: Homepage, https://github.com/Zeit-Geist/ptcal
Project-URL: Bug Tracker, https://github.com/Zeit-Geist/ptcal/issues
Project-URL: Documentation, https://github.com/Zeit-Geist/ptcal#readme
Keywords: pt100,pt25,calibration,temperature,its-90,cvd,iec60751,metrology,measurement,fitting,curve,kennlinie,laboratory
Classifier: Development Status :: 4 - Beta
Classifier: Intended Audience :: Science/Research
Classifier: Intended Audience :: Manufacturing
Classifier: Topic :: Scientific/Engineering :: Physics
Classifier: Topic :: Scientific/Engineering :: Information Analysis
Classifier: License :: OSI Approved :: MIT License
Classifier: Programming Language :: Python :: 3
Classifier: Programming Language :: Python :: 3.9
Classifier: Programming Language :: Python :: 3.10
Classifier: Programming Language :: Python :: 3.11
Classifier: Programming Language :: Python :: 3.12
Classifier: Operating System :: OS Independent
Requires-Python: >=3.9
License-File: LICENSE
Requires-Dist: numpy>=1.20
Requires-Dist: pandas>=1.3
Requires-Dist: scipy>=1.7
Requires-Dist: matplotlib>=3.4
Requires-Dist: xlsxwriter>=3.0
Requires-Dist: openpyxl>=3.0
Dynamic: license-file
